.mica_settings
.project
.pydevproject
MANIFEST.in
ez_setup.py
setup.py
.settings/org.eclipse.core.resources.prefs
.settings/org.eclipse.ltk.core.refactoring.prefs
hildon/zourite.desktop
hildon/icons/48x48/zourite.png
hildon/icons/64x64/zourite.png
nbproject/project.properties
nbproject/project.xml
scripts/zourite
scripts/zourite-setup
scripts/zourite-setup-force
src/zourite/__init__.py
src/zourite/bootstrap.py
src/zourite/email_message_editor.png
src/zourite/gdata-contacts-icon.png
src/zourite/general_call.png
src/zourite/general_default_avatar.png
src/zourite/linkedin.png
src/zourite/zourite-logo.png
src/zourite.egg-info/PKG-INFO
src/zourite.egg-info/SOURCES.txt
src/zourite.egg-info/dependency_links.txt
src/zourite.egg-info/not-zip-safe
src/zourite.egg-info/top_level.txt
src/zourite/common/__init__.py
src/zourite/common/version.py
src/zourite/core/__init__.py
src/zourite/core/plugin.py
src/zourite/core/zourite.py
src/zourite/gui/__init__.py
src/zourite/gui/mock.py
src/zourite/gui/zouriteGui.py
src/zourite/plugin/__init__.py
src/zourite/plugin/gmail/__init__.py
src/zourite/plugin/gmail/gmailplugin.py
src/zourite/plugin/linkedin/__init__.py
src/zourite/plugin/linkedin/linkedin.py
src/zourite/plugin/linkedin/linkedinplugin.py
src/zourite/plugin/linkedin/oauth.py