Metadata-Version: 1.0
Name: zourite
Version: 0.4.0
Summary: Zourite Professional Networking Application for N900
Home-page: http://blog.zourite.bressure.net
Author: Thierry Bressure
Author-email: zourite@bressure.net
License: UNKNOWN
Download-URL: http://zourite.bressure.net
Platform: UNKNOWN
Classifier: Development Status :: 4 - Beta
Classifier: Environment :: Handhelds/PDA's
Classifier: Intended Audience :: End Users/Desktop
Classifier: Intended Audience :: Developers
Classifier: License :: OSI Approved :: GNU Library or Lesser General Public License (LGPL)
Classifier: Operating System :: POSIX :: Linux
Classifier: Programming Language :: Python
Classifier: Topic :: Communications :: Email
Classifier: Topic :: Office/Business
